[
  {
    "ContainingType": "ApiPeliculas.Controllers.pelicula_salacineController",
    "Method": "Getpelicula_salacines",
    "RelativePath": "api/pelicula_salacine",
    "HttpMethod": "GET",
    "IsController": true,
    "Order": 0,
    "Parameters": [],
    "ReturnTypes": [
      {
        "Type": "System.Collections.Generic.IEnumerable\u00601[[PracFullStack.Models.pelicula_salacine, PracFullStack, Version=1.0.0.0, Culture=neutral, PublicKeyToken=null]]",
        "MediaTypes": [
          "text/plain",
          "application/json",
          "text/json"
        ],
        "StatusCode": 200
      }
    ]
  },
  {
    "ContainingType": "ApiPeliculas.Controllers.pelicula_salacineController",
    "Method": "Postpelicula_salacine",
    "RelativePath": "api/pelicula_salacine",
    "HttpMethod": "POST",
    "IsController": true,
    "Order": 0,
    "Parameters": [
      {
        "Name": "pelicula_salacine",
        "Type": "PracFullStack.Models.pelicula_salacine",
        "IsRequired": true
      }
    ],
    "ReturnTypes": [
      {
        "Type": "PracFullStack.Models.pelicula_salacine",
        "MediaTypes": [
          "text/plain",
          "application/json",
          "text/json"
        ],
        "StatusCode": 200
      }
    ]
  },
  {
    "ContainingType": "ApiPeliculas.Controllers.pelicula_salacineController",
    "Method": "Getpelicula_salacine",
    "RelativePath": "api/pelicula_salacine/{id}",
    "HttpMethod": "GET",
    "IsController": true,
    "Order": 0,
    "Parameters": [
      {
        "Name": "id",
        "Type": "System.Int32",
        "IsRequired": true
      }
    ],
    "ReturnTypes": [
      {
        "Type": "PracFullStack.Models.pelicula_salacine",
        "MediaTypes": [
          "text/plain",
          "application/json",
          "text/json"
        ],
        "StatusCode": 200
      }
    ]
  },
  {
    "ContainingType": "ApiPeliculas.Controllers.pelicula_salacineController",
    "Method": "Putpelicula_salacine",
    "RelativePath": "api/pelicula_salacine/{id}",
    "HttpMethod": "PUT",
    "IsController": true,
    "Order": 0,
    "Parameters": [
      {
        "Name": "id",
        "Type": "System.Int32",
        "IsRequired": true
      },
      {
        "Name": "pelicula_salacine",
        "Type": "PracFullStack.Models.pelicula_salacine",
        "IsRequired": true
      }
    ],
    "ReturnTypes": []
  },
  {
    "ContainingType": "ApiPeliculas.Controllers.pelicula_salacineController",
    "Method": "Deletepelicula_salacine",
    "RelativePath": "api/pelicula_salacine/{id}",
    "HttpMethod": "DELETE",
    "IsController": true,
    "Order": 0,
    "Parameters": [
      {
        "Name": "id",
        "Type": "System.Int32",
        "IsRequired": true
      }
    ],
    "ReturnTypes": []
  },
  {
    "ContainingType": "ApiPeliculas.Controllers.pelicula_salacineController",
    "Method": "Desactive",
    "RelativePath": "api/pelicula_salacine/desactive/{id}",
    "HttpMethod": "PUT",
    "IsController": true,
    "Order": 0,
    "Parameters": [
      {
        "Name": "id",
        "Type": "System.Int32",
        "IsRequired": true
      }
    ],
    "ReturnTypes": []
  },
  {
    "ContainingType": "ApiPeliculas.Controllers.pelicula_salacineController",
    "Method": "GetResultado",
    "RelativePath": "api/pelicula_salacine/disponibilidad /{nombre_sala}",
    "HttpMethod": "GET",
    "IsController": true,
    "Order": 0,
    "Parameters": [
      {
        "Name": "nombre_sala",
        "Type": "System.String",
        "IsRequired": true
      }
    ],
    "ReturnTypes": [
      {
        "Type": "System.String",
        "MediaTypes": [
          "text/plain",
          "application/json",
          "text/json"
        ],
        "StatusCode": 200
      }
    ]
  },
  {
    "ContainingType": "ApiPeliculas.Controllers.pelicula_salacineController",
    "Method": "GetSearch",
    "RelativePath": "api/pelicula_salacine/search",
    "HttpMethod": "GET",
    "IsController": true,
    "Order": 0,
    "Parameters": [
      {
        "Name": "search",
        "Type": "System.String",
        "IsRequired": false
      }
    ],
    "ReturnTypes": [
      {
        "Type": "PracFullStack.Models.pelicula_salacine",
        "MediaTypes": [
          "text/plain",
          "application/json",
          "text/json"
        ],
        "StatusCode": 200
      }
    ]
  },
  {
    "ContainingType": "ApiPeliculas.Controllers.peliculasController",
    "Method": "GetPeliculas",
    "RelativePath": "api/peliculas",
    "HttpMethod": "GET",
    "IsController": true,
    "Order": 0,
    "Parameters": [],
    "ReturnTypes": [
      {
        "Type": "System.Collections.Generic.IEnumerable\u00601[[PracFullStack.Models.pelicula, PracFullStack, Version=1.0.0.0, Culture=neutral, PublicKeyToken=null]]",
        "MediaTypes": [
          "text/plain",
          "application/json",
          "text/json"
        ],
        "StatusCode": 200
      }
    ]
  },
  {
    "ContainingType": "ApiPeliculas.Controllers.peliculasController",
    "Method": "PostPelicula",
    "RelativePath": "api/peliculas",
    "HttpMethod": "POST",
    "IsController": true,
    "Order": 0,
    "Parameters": [
      {
        "Name": "peli",
        "Type": "PracFullStack.Models.pelicula",
        "IsRequired": true
      }
    ],
    "ReturnTypes": [
      {
        "Type": "PracFullStack.Models.pelicula",
        "MediaTypes": [
          "text/plain",
          "application/json",
          "text/json"
        ],
        "StatusCode": 200
      }
    ]
  },
  {
    "ContainingType": "ApiPeliculas.Controllers.peliculasController",
    "Method": "GetPeliculaId",
    "RelativePath": "api/peliculas/{id}",
    "HttpMethod": "GET",
    "IsController": true,
    "Order": 0,
    "Parameters": [
      {
        "Name": "id",
        "Type": "System.Int32",
        "IsRequired": true
      }
    ],
    "ReturnTypes": [
      {
        "Type": "PracFullStack.Models.pelicula",
        "MediaTypes": [
          "text/plain",
          "application/json",
          "text/json"
        ],
        "StatusCode": 200
      }
    ]
  },
  {
    "ContainingType": "ApiPeliculas.Controllers.peliculasController",
    "Method": "PostPelicul",
    "RelativePath": "api/peliculas/{id}",
    "HttpMethod": "PUT",
    "IsController": true,
    "Order": 0,
    "Parameters": [
      {
        "Name": "id",
        "Type": "System.Int32",
        "IsRequired": true
      },
      {
        "Name": "peli",
        "Type": "PracFullStack.Models.pelicula",
        "IsRequired": true
      }
    ],
    "ReturnTypes": []
  },
  {
    "ContainingType": "ApiPeliculas.Controllers.peliculasController",
    "Method": "DeletePelicula",
    "RelativePath": "api/peliculas/{id}",
    "HttpMethod": "DELETE",
    "IsController": true,
    "Order": 0,
    "Parameters": [
      {
        "Name": "id",
        "Type": "System.Int32",
        "IsRequired": true
      }
    ],
    "ReturnTypes": []
  },
  {
    "ContainingType": "ApiPeliculas.Controllers.peliculasController",
    "Method": "DesactivatePelicula",
    "RelativePath": "api/peliculas/desactivate/{id}",
    "HttpMethod": "PUT",
    "IsController": true,
    "Order": 0,
    "Parameters": [
      {
        "Name": "id",
        "Type": "System.Int32",
        "IsRequired": true
      }
    ],
    "ReturnTypes": []
  },
  {
    "ContainingType": "ApiPeliculas.Controllers.peliculasController",
    "Method": "GetSearch",
    "RelativePath": "api/peliculas/search",
    "HttpMethod": "GET",
    "IsController": true,
    "Order": 0,
    "Parameters": [
      {
        "Name": "search",
        "Type": "System.String",
        "IsRequired": false
      }
    ],
    "ReturnTypes": [
      {
        "Type": "PracFullStack.Models.pelicula",
        "MediaTypes": [
          "text/plain",
          "application/json",
          "text/json"
        ],
        "StatusCode": 200
      }
    ]
  },
  {
    "ContainingType": "ApiPeliculas.Controllers.peliculasController",
    "Method": "GetPeliculaByFecha",
    "RelativePath": "api/peliculas/searchFecha/{fecha}",
    "HttpMethod": "GET",
    "IsController": true,
    "Order": 0,
    "Parameters": [
      {
        "Name": "fecha",
        "Type": "System.DateTime",
        "IsRequired": true
      }
    ],
    "ReturnTypes": [
      {
        "Type": "PracFullStack.Models.pelicula",
        "MediaTypes": [
          "text/plain",
          "application/json",
          "text/json"
        ],
        "StatusCode": 200
      }
    ]
  },
  {
    "ContainingType": "ApiPeliculas.Controllers.sala_cineController",
    "Method": "Getsala_cines",
    "RelativePath": "api/sala_cine",
    "HttpMethod": "GET",
    "IsController": true,
    "Order": 0,
    "Parameters": [],
    "ReturnTypes": [
      {
        "Type": "System.Collections.Generic.IEnumerable\u00601[[PracFullStack.Models.sala_cine, PracFullStack, Version=1.0.0.0, Culture=neutral, PublicKeyToken=null]]",
        "MediaTypes": [
          "text/plain",
          "application/json",
          "text/json"
        ],
        "StatusCode": 200
      }
    ]
  },
  {
    "ContainingType": "ApiPeliculas.Controllers.sala_cineController",
    "Method": "Postsala_cine",
    "RelativePath": "api/sala_cine",
    "HttpMethod": "POST",
    "IsController": true,
    "Order": 0,
    "Parameters": [
      {
        "Name": "sala_cine",
        "Type": "PracFullStack.Models.sala_cine",
        "IsRequired": true
      }
    ],
    "ReturnTypes": [
      {
        "Type": "PracFullStack.Models.sala_cine",
        "MediaTypes": [
          "text/plain",
          "application/json",
          "text/json"
        ],
        "StatusCode": 200
      }
    ]
  },
  {
    "ContainingType": "ApiPeliculas.Controllers.sala_cineController",
    "Method": "Getsala_cine",
    "RelativePath": "api/sala_cine/{id}",
    "HttpMethod": "GET",
    "IsController": true,
    "Order": 0,
    "Parameters": [
      {
        "Name": "id",
        "Type": "System.Int32",
        "IsRequired": true
      }
    ],
    "ReturnTypes": [
      {
        "Type": "PracFullStack.Models.sala_cine",
        "MediaTypes": [
          "text/plain",
          "application/json",
          "text/json"
        ],
        "StatusCode": 200
      }
    ]
  },
  {
    "ContainingType": "ApiPeliculas.Controllers.sala_cineController",
    "Method": "Putsala_cine",
    "RelativePath": "api/sala_cine/{id}",
    "HttpMethod": "PUT",
    "IsController": true,
    "Order": 0,
    "Parameters": [
      {
        "Name": "id",
        "Type": "System.Int32",
        "IsRequired": true
      },
      {
        "Name": "sala_cine",
        "Type": "PracFullStack.Models.sala_cine",
        "IsRequired": true
      }
    ],
    "ReturnTypes": []
  },
  {
    "ContainingType": "ApiPeliculas.Controllers.sala_cineController",
    "Method": "Deletesala_cine",
    "RelativePath": "api/sala_cine/{id}",
    "HttpMethod": "DELETE",
    "IsController": true,
    "Order": 0,
    "Parameters": [
      {
        "Name": "id",
        "Type": "System.Int32",
        "IsRequired": true
      }
    ],
    "ReturnTypes": []
  },
  {
    "ContainingType": "ApiPeliculas.Controllers.sala_cineController",
    "Method": "DesactivateSala",
    "RelativePath": "api/sala_cine/desactivate/{id}",
    "HttpMethod": "PUT",
    "IsController": true,
    "Order": 0,
    "Parameters": [
      {
        "Name": "id",
        "Type": "System.Int32",
        "IsRequired": true
      }
    ],
    "ReturnTypes": []
  },
  {
    "ContainingType": "ApiPeliculas.Controllers.sala_cineController",
    "Method": "GetDisponible",
    "RelativePath": "api/sala_cine/disponibilidad/{nombre_sala}",
    "HttpMethod": "GET",
    "IsController": true,
    "Order": 0,
    "Parameters": [
      {
        "Name": "nombre_sala",
        "Type": "System.String",
        "IsRequired": true
      }
    ],
    "ReturnTypes": [
      {
        "Type": "System.String",
        "MediaTypes": [
          "text/plain",
          "application/json",
          "text/json"
        ],
        "StatusCode": 200
      }
    ]
  },
  {
    "ContainingType": "ApiPeliculas.Controllers.sala_cineController",
    "Method": "SearchSala",
    "RelativePath": "api/sala_cine/search",
    "HttpMethod": "GET",
    "IsController": true,
    "Order": 0,
    "Parameters": [
      {
        "Name": "search",
        "Type": "System.String",
        "IsRequired": false
      }
    ],
    "ReturnTypes": [
      {
        "Type": "PracFullStack.Models.sala_cine",
        "MediaTypes": [
          "text/plain",
          "application/json",
          "text/json"
        ],
        "StatusCode": 200
      }
    ]
  },
  {
    "ContainingType": "ApiPeliculas.Controllers.WeatherForecastController",
    "Method": "Get",
    "RelativePath": "WeatherForecast",
    "HttpMethod": "GET",
    "IsController": true,
    "Order": 0,
    "Parameters": [],
    "ReturnTypes": [
      {
        "Type": "System.Collections.Generic.IEnumerable\u00601[[ApiPeliculas.WeatherForecast, ApiPeliculas, Version=1.0.0.0, Culture=neutral, PublicKeyToken=null]]",
        "MediaTypes": [
          "text/plain",
          "application/json",
          "text/json"
        ],
        "StatusCode": 200
      }
    ],
    "EndpointName": "GetWeatherForecast"
  }
]